unicef_notification/__init__.py
unicef_notification/admin.py
unicef_notification/backends.py
unicef_notification/loaders.py
unicef_notification/models.py
unicef_notification/utils.py
unicef_notification/validations.py
unicef_notification/management/__init__.py
unicef_notification/management/commands/__init__.py
unicef_notification/management/commands/update_notifications.py
unicef_notification/migrations/0001_initial.py
unicef_notification/migrations/__init__.py
unicef_notification-1.4.1.dist-info/METADATA
unicef_notification-1.4.1.dist-info/WHEEL
unicef_notification-1.4.1.dist-info/licenses/LICENSE
unicef_notification-1.4.1.dist-info/RECORD
