Metadata-Version: 2.3
Name: unicef-notification
Version: 1.4.1
Summary: Django package that handles sending of notifications
Project-URL: Homepage, https://github.com/unicef/unicef-notification
Author-email: UNICEF <dev@unicef.org>
License-Expression: Apache-2.0 OR MIT
License-File: LICENSE
Classifier: Environment :: Web Environment
Classifier: Framework :: Django
Classifier: Framework :: Django :: 3.2
Classifier: Framework :: Django :: 4.2
Classifier: Framework :: Django :: 5.0
Classifier: Intended Audience :: Developers
Classifier: Programming Language :: Python
Classifier: Programming Language :: Python :: 3.11
Classifier: Programming Language :: Python :: 3.12
Requires-Dist: django
Requires-Dist: django-model-utils
Requires-Dist: django-post-office
Requires-Dist: setuptools
Provides-Extra: test
Requires-Dist: black; extra == 'test'
Requires-Dist: factory-boy; extra == 'test'
Requires-Dist: flake8; extra == 'test'
Requires-Dist: isort; extra == 'test'
Requires-Dist: psycopg2-binary; extra == 'test'
Requires-Dist: pytest; extra == 'test'
Requires-Dist: pytest-cov; extra == 'test'
Requires-Dist: pytest-django; extra == 'test'
Requires-Dist: pytest-echo; extra == 'test'
